{"name":"web","classpathEntries":[{"kind":"binary","path":"D:\\Program Files\\Java\\jdk1.8.0_171\\jre\\lib\\resources.jar","javadocContainerUrl":"https://docs.oracle.com/javase/1/docs/api/","isSystem":true,"isOwn":false,"isTest":false,"isJavaContent":false},{"kind":"binary","path":"D:\\Program Files\\Java\\jdk1.8.0_171\\jre\\lib\\rt.jar","javadocContainerUrl":"https://docs.oracle.com/javase/1/docs/api/","isSystem":true,"isOwn":false,"isTest":false,"isJavaContent":false},{"kind":"binary","path":"D:\\Program Files\\Java\\jdk1.8.0_171\\jre\\lib\\jsse.jar","javadocContainerUrl":"https://docs.oracle.com/javase/1/docs/api/","isSystem":true,"isOwn":false,"isTest":false,"isJavaContent":false},{"kind":"binary","path":"D:\\Program Files\\Java\\jdk1.8.0_171\\jre\\lib\\jce.jar","javadocContainerUrl":"https://docs.oracle.com/javase/1/docs/api/","isSystem":true,"isOwn":false,"isTest":false,"isJavaContent":false},{"kind":"binary","path":"D:\\Program Files\\Java\\jdk1.8.0_171\\jre\\lib\\charsets.jar","javadocContainerUrl":"https://docs.oracle.com/javase/1/docs/api/","isSystem":true,"isOwn":false,"isTest":false,"isJavaContent":false},{"kind":"binary","path":"D:\\Program Files\\Java\\jdk1.8.0_171\\jre\\lib\\jfr.jar","javadocContainerUrl":"https://docs.oracle.com/javase/1/docs/api/","isSystem":true,"isOwn":false,"isTest":false,"isJavaContent":false},{"kind":"source","path":"D:\\myGit\\SSFBlog\\src\\parent\\pojo\\src\\main\\java","outputFolder":"D:\\myGit\\SSFBlog\\src\\parent\\pojo\\target\\classes","javadocContainerUrl":"file:/D:/myGit/SSFBlog/src/parent/pojo/target/site/apidocs","isSystem":false,"isOwn":false,"isTest":false,"isJavaContent":true},{"kind":"binary","path":"C:\\Users\\L460\\.m2\\repository\\org\\jsoup\\jsoup\\1.10.3\\jsoup-1.10.3.jar","sourceContainerUrl":"file:/C:/Users/L460/.m2/repository/org/jsoup/jsoup/1.10.3/jsoup-1.10.3-sources.jar","javadocContainerUrl":"file:/C:/Users/L460/.m2/repository/org/jsoup/jsoup/1.10.3/jsoup-1.10.3-javadoc.jar","isSystem":false,"isOwn":false,"isTest":false,"isJavaContent":false},{"kind":"binary","path":"C:\\Users\\L460\\.m2\\repository\\org\\apache\\poi\\poi\\3.14\\poi-3.14.jar","sourceContainerUrl":"file:/C:/Users/L460/.m2/repository/org/apache/poi/poi/3.14/poi-3.14-sources.jar","javadocContainerUrl":"file:/C:/Users/L460/.m2/repository/org/apache/poi/poi/3.14/poi-3.14-javadoc.jar","isSystem":false,"isOwn":false,"isTest":false,"isJavaContent":false},{"kind":"binary","path":"C:\\Users\\L460\\.m2\\repository\\commons-codec\\commons-codec\\1.10\\commons-codec-1.10.jar","sourceContainerUrl":"file:/C:/Users/L460/.m2/repository/commons-codec/commons-codec/1.10/commons-codec-1.10-sources.jar","javadocContainerUrl":"file:/C:/Users/L460/.m2/repository/commons-codec/commons-codec/1.10/commons-codec-1.10-javadoc.jar","isSystem":false,"isOwn":false,"isTest":false,"isJavaContent":false},{"kind":"binary","path":"C:\\Users\\L460\\.m2\\repository\\org\\anarres\\lzo\\lzo-core\\1.0.0\\lzo-core-1.0.0.jar","sourceContainerUrl":"file:/C:/Users/L460/.m2/repository/org/anarres/lzo/lzo-core/1.0.0/lzo-core-1.0.0-sources.jar","javadocContainerUrl":"file:/C:/Users/L460/.m2/repository/org/anarres/lzo/lzo-core/1.0.0/lzo-core-1.0.0-javadoc.jar","isSystem":false,"isOwn":false,"isTest":false,"isJavaContent":false},{"kind":"binary","path":"C:\\Users\\L460\\.m2\\repository\\commons-logging\\commons-logging\\1.1.1\\commons-logging-1.1.1.jar","sourceContainerUrl":"file:/C:/Users/L460/.m2/repository/commons-logging/commons-logging/1.1.1/commons-logging-1.1.1-sources.jar","javadocContainerUrl":"file:/C:/Users/L460/.m2/repository/commons-logging/commons-logging/1.1.1/commons-logging-1.1.1-javadoc.jar","isSystem":false,"isOwn":false,"isTest":false,"isJavaContent":false},{"kind":"binary","path":"C:\\Users\\L460\\.m2\\repository\\com\\google\\code\\findbugs\\jsr305\\2.0.2\\jsr305-2.0.2.jar","isSystem":false,"isOwn":false,"isTest":false,"isJavaContent":false},{"kind":"binary","path":"C:\\Users\\L460\\.m2\\repository\\com\\h2database\\h2\\1.4.197\\h2-1.4.197.jar","sourceContainerUrl":"file:/C:/Users/L460/.m2/repository/com/h2database/h2/1.4.197/h2-1.4.197-sources.jar","javadocContainerUrl":"file:/C:/Users/L460/.m2/repository/com/h2database/h2/1.4.197/h2-1.4.197-javadoc.jar","isSystem":false,"isOwn":false,"isTest":false,"isJavaContent":false},{"kind":"binary","path":"C:\\Users\\L460\\.m2\\repository\\org\\apache\\commons\\commons-lang3\\3.4\\commons-lang3-3.4.jar","sourceContainerUrl":"file:/C:/Users/L460/.m2/repository/org/apache/commons/commons-lang3/3.4/commons-lang3-3.4-sources.jar","javadocContainerUrl":"file:/C:/Users/L460/.m2/repository/org/apache/commons/commons-lang3/3.4/commons-lang3-3.4-javadoc.jar","isSystem":false,"isOwn":false,"isTest":false,"isJavaContent":false},{"kind":"binary","path":"C:\\Users\\L460\\.m2\\repository\\javax\\validation\\validation-api\\1.1.0.Final\\validation-api-1.1.0.Final.jar","sourceContainerUrl":"file:/C:/Users/L460/.m2/repository/javax/validation/validation-api/1.1.0.Final/validation-api-1.1.0.Final-sources.jar","javadocContainerUrl":"file:/C:/Users/L460/.m2/repository/javax/validation/validation-api/1.1.0.Final/validation-api-1.1.0.Final-javadoc.jar","isSystem":false,"isOwn":false,"isTest":false,"isJavaContent":false},{"kind":"binary","path":"C:\\Users\\L460\\.m2\\repository\\org\\hibernate\\hibernate-validator\\5.2.4.Final\\hibernate-validator-5.2.4.Final.jar","sourceContainerUrl":"file:/C:/Users/L460/.m2/repository/org/hibernate/hibernate-validator/5.2.4.Final/hibernate-validator-5.2.4.Final-sources.jar","isSystem":false,"isOwn":false,"isTest":false,"isJavaContent":false},{"kind":"binary","path":"C:\\Users\\L460\\.m2\\repository\\org\\jboss\\logging\\jboss-logging\\3.2.1.Final\\jboss-logging-3.2.1.Final.jar","sourceContainerUrl":"file:/C:/Users/L460/.m2/repository/org/jboss/logging/jboss-logging/3.2.1.Final/jboss-logging-3.2.1.Final-sources.jar","isSystem":false,"isOwn":false,"isTest":false,"isJavaContent":false},{"kind":"binary","path":"C:\\Users\\L460\\.m2\\repository\\com\\fasterxml\\classmate\\1.1.0\\classmate-1.1.0.jar","sourceContainerUrl":"file:/C:/Users/L460/.m2/repository/com/fasterxml/classmate/1.1.0/classmate-1.1.0-sources.jar","javadocContainerUrl":"file:/C:/Users/L460/.m2/repository/com/fasterxml/classmate/1.1.0/classmate-1.1.0-javadoc.jar","isSystem":false,"isOwn":false,"isTest":false,"isJavaContent":false},{"kind":"binary","path":"C:\\Users\\L460\\.m2\\repository\\com\\squareup\\okhttp3\\okhttp\\3.8.1\\okhttp-3.8.1.jar","sourceContainerUrl":"file:/C:/Users/L460/.m2/repository/com/squareup/okhttp3/okhttp/3.8.1/okhttp-3.8.1-sources.jar","javadocContainerUrl":"file:/C:/Users/L460/.m2/repository/com/squareup/okhttp3/okhttp/3.8.1/okhttp-3.8.1-javadoc.jar","isSystem":false,"isOwn":false,"isTest":false,"isJavaContent":false},{"kind":"binary","path":"C:\\Users\\L460\\.m2\\repository\\com\\squareup\\okio\\okio\\1.13.0\\okio-1.13.0.jar","sourceContainerUrl":"file:/C:/Users/L460/.m2/repository/com/squareup/okio/okio/1.13.0/okio-1.13.0-sources.jar","javadocContainerUrl":"file:/C:/Users/L460/.m2/repository/com/squareup/okio/okio/1.13.0/okio-1.13.0-javadoc.jar","isSystem":false,"isOwn":false,"isTest":false,"isJavaContent":false},{"kind":"binary","path":"C:\\Users\\L460\\.m2\\repository\\org\\springframework\\spring-context-support\\4.2.5.RELEASE\\spring-context-support-4.2.5.RELEASE.jar","sourceContainerUrl":"file:/C:/Users/L460/.m2/repository/org/springframework/spring-context-support/4.2.5.RELEASE/spring-context-support-4.2.5.RELEASE-sources.jar","javadocContainerUrl":"file:/C:/Users/L460/.m2/repository/org/springframework/spring-context-support/4.2.5.RELEASE/spring-context-support-4.2.5.RELEASE-javadoc.jar","isSystem":false,"isOwn":false,"isTest":false,"isJavaContent":false},{"kind":"binary","path":"C:\\Users\\L460\\.m2\\repository\\org\\springframework\\spring-beans\\4.2.5.RELEASE\\spring-beans-4.2.5.RELEASE.jar","sourceContainerUrl":"file:/C:/Users/L460/.m2/repository/org/springframework/spring-beans/4.2.5.RELEASE/spring-beans-4.2.5.RELEASE-sources.jar","javadocContainerUrl":"file:/C:/Users/L460/.m2/repository/org/springframework/spring-beans/4.2.5.RELEASE/spring-beans-4.2.5.RELEASE-javadoc.jar","isSystem":false,"isOwn":false,"isTest":false,"isJavaContent":false},{"kind":"binary","path":"C:\\Users\\L460\\.m2\\repository\\org\\springframework\\spring-core\\4.2.5.RELEASE\\spring-core-4.2.5.RELEASE.jar","sourceContainerUrl":"file:/C:/Users/L460/.m2/repository/org/springframework/spring-core/4.2.5.RELEASE/spring-core-4.2.5.RELEASE-sources.jar","javadocContainerUrl":"file:/C:/Users/L460/.m2/repository/org/springframework/spring-core/4.2.5.RELEASE/spring-core-4.2.5.RELEASE-javadoc.jar","isSystem":false,"isOwn":false,"isTest":false,"isJavaContent":false},{"kind":"binary","path":"C:\\Users\\L460\\.m2\\repository\\org\\springframework\\spring-web\\4.2.5.RELEASE\\spring-web-4.2.5.RELEASE.jar","sourceContainerUrl":"file:/C:/Users/L460/.m2/repository/org/springframework/spring-web/4.2.5.RELEASE/spring-web-4.2.5.RELEASE-sources.jar","javadocContainerUrl":"file:/C:/Users/L460/.m2/repository/org/springframework/spring-web/4.2.5.RELEASE/spring-web-4.2.5.RELEASE-javadoc.jar","isSystem":false,"isOwn":false,"isTest":false,"isJavaContent":false},{"kind":"binary","path":"C:\\Users\\L460\\.m2\\repository\\org\\springframework\\spring-websocket\\4.2.5.RELEASE\\spring-websocket-4.2.5.RELEASE.jar","sourceContainerUrl":"file:/C:/Users/L460/.m2/repository/org/springframework/spring-websocket/4.2.5.RELEASE/spring-websocket-4.2.5.RELEASE-sources.jar","javadocContainerUrl":"file:/C:/Users/L460/.m2/repository/org/springframework/spring-websocket/4.2.5.RELEASE/spring-websocket-4.2.5.RELEASE-javadoc.jar","isSystem":false,"isOwn":false,"isTest":false,"isJavaContent":false},{"kind":"binary","path":"C:\\Users\\L460\\.m2\\repository\\org\\springframework\\spring-webmvc\\4.2.5.RELEASE\\spring-webmvc-4.2.5.RELEASE.jar","sourceContainerUrl":"file:/C:/Users/L460/.m2/repository/org/springframework/spring-webmvc/4.2.5.RELEASE/spring-webmvc-4.2.5.RELEASE-sources.jar","javadocContainerUrl":"file:/C:/Users/L460/.m2/repository/org/springframework/spring-webmvc/4.2.5.RELEASE/spring-webmvc-4.2.5.RELEASE-javadoc.jar","isSystem":false,"isOwn":false,"isTest":false,"isJavaContent":false},{"kind":"binary","path":"C:\\Users\\L460\\.m2\\repository\\org\\springframework\\spring-expression\\4.2.5.RELEASE\\spring-expression-4.2.5.RELEASE.jar","sourceContainerUrl":"file:/C:/Users/L460/.m2/repository/org/springframework/spring-expression/4.2.5.RELEASE/spring-expression-4.2.5.RELEASE-sources.jar","javadocContainerUrl":"file:/C:/Users/L460/.m2/repository/org/springframework/spring-expression/4.2.5.RELEASE/spring-expression-4.2.5.RELEASE-javadoc.jar","isSystem":false,"isOwn":false,"isTest":false,"isJavaContent":false},{"kind":"binary","path":"C:\\Users\\L460\\.m2\\repository\\org\\springframework\\spring-context\\4.2.5.RELEASE\\spring-context-4.2.5.RELEASE.jar","sourceContainerUrl":"file:/C:/Users/L460/.m2/repository/org/springframework/spring-context/4.2.5.RELEASE/spring-context-4.2.5.RELEASE-sources.jar","javadocContainerUrl":"file:/C:/Users/L460/.m2/repository/org/springframework/spring-context/4.2.5.RELEASE/spring-context-4.2.5.RELEASE-javadoc.jar","isSystem":false,"isOwn":false,"isTest":false,"isJavaContent":false},{"kind":"binary","path":"C:\\Users\\L460\\.m2\\repository\\org\\springframework\\spring-orm\\4.2.5.RELEASE\\spring-orm-4.2.5.RELEASE.jar","sourceContainerUrl":"file:/C:/Users/L460/.m2/repository/org/springframework/spring-orm/4.2.5.RELEASE/spring-orm-4.2.5.RELEASE-sources.jar","javadocContainerUrl":"file:/C:/Users/L460/.m2/repository/org/springframework/spring-orm/4.2.5.RELEASE/spring-orm-4.2.5.RELEASE-javadoc.jar","isSystem":false,"isOwn":false,"isTest":false,"isJavaContent":false},{"kind":"binary","path":"C:\\Users\\L460\\.m2\\repository\\org\\springframework\\spring-jdbc\\4.2.5.RELEASE\\spring-jdbc-4.2.5.RELEASE.jar","sourceContainerUrl":"file:/C:/Users/L460/.m2/repository/org/springframework/spring-jdbc/4.2.5.RELEASE/spring-jdbc-4.2.5.RELEASE-sources.jar","javadocContainerUrl":"file:/C:/Users/L460/.m2/repository/org/springframework/spring-jdbc/4.2.5.RELEASE/spring-jdbc-4.2.5.RELEASE-javadoc.jar","isSystem":false,"isOwn":false,"isTest":false,"isJavaContent":false},{"kind":"binary","path":"C:\\Users\\L460\\.m2\\repository\\org\\springframework\\data\\spring-data-jpa\\1.11.1.RELEASE\\spring-data-jpa-1.11.1.RELEASE.jar","sourceContainerUrl":"file:/C:/Users/L460/.m2/repository/org/springframework/data/spring-data-jpa/1.11.1.RELEASE/spring-data-jpa-1.11.1.RELEASE-sources.jar","javadocContainerUrl":"file:/C:/Users/L460/.m2/repository/org/springframework/data/spring-data-jpa/1.11.1.RELEASE/spring-data-jpa-1.11.1.RELEASE-javadoc.jar","isSystem":false,"isOwn":false,"isTest":false,"isJavaContent":false},{"kind":"binary","path":"C:\\Users\\L460\\.m2\\repository\\org\\springframework\\data\\spring-data-commons\\1.13.1.RELEASE\\spring-data-commons-1.13.1.RELEASE.jar","sourceContainerUrl":"file:/C:/Users/L460/.m2/repository/org/springframework/data/spring-data-commons/1.13.1.RELEASE/spring-data-commons-1.13.1.RELEASE-sources.jar","javadocContainerUrl":"file:/C:/Users/L460/.m2/repository/org/springframework/data/spring-data-commons/1.13.1.RELEASE/spring-data-commons-1.13.1.RELEASE-javadoc.jar","isSystem":false,"isOwn":false,"isTest":false,"isJavaContent":false},{"kind":"binary","path":"C:\\Users\\L460\\.m2\\repository\\org\\aspectj\\aspectjrt\\1.8.10\\aspectjrt-1.8.10.jar","sourceContainerUrl":"file:/C:/Users/L460/.m2/repository/org/aspectj/aspectjrt/1.8.10/aspectjrt-1.8.10-sources.jar","javadocContainerUrl":"file:/C:/Users/L460/.m2/repository/org/aspectj/aspectjrt/1.8.10/aspectjrt-1.8.10-javadoc.jar","isSystem":false,"isOwn":false,"isTest":false,"isJavaContent":false},{"kind":"binary","path":"C:\\Users\\L460\\.m2\\repository\\org\\slf4j\\jcl-over-slf4j\\1.7.24\\jcl-over-slf4j-1.7.24.jar","sourceContainerUrl":"file:/C:/Users/L460/.m2/repository/org/slf4j/jcl-over-slf4j/1.7.24/jcl-over-slf4j-1.7.24-sources.jar","javadocContainerUrl":"file:/C:/Users/L460/.m2/repository/org/slf4j/jcl-over-slf4j/1.7.24/jcl-over-slf4j-1.7.24-javadoc.jar","isSystem":false,"isOwn":false,"isTest":false,"isJavaContent":false},{"kind":"binary","path":"C:\\Users\\L460\\.m2\\repository\\org\\springframework\\spring-aop\\4.2.5.RELEASE\\spring-aop-4.2.5.RELEASE.jar","sourceContainerUrl":"file:/C:/Users/L460/.m2/repository/org/springframework/spring-aop/4.2.5.RELEASE/spring-aop-4.2.5.RELEASE-sources.jar","javadocContainerUrl":"file:/C:/Users/L460/.m2/repository/org/springframework/spring-aop/4.2.5.RELEASE/spring-aop-4.2.5.RELEASE-javadoc.jar","isSystem":false,"isOwn":false,"isTest":false,"isJavaContent":false},{"kind":"binary","path":"C:\\Users\\L460\\.m2\\repository\\aopalliance\\aopalliance\\1.0\\aopalliance-1.0.jar","sourceContainerUrl":"file:/C:/Users/L460/.m2/repository/aopalliance/aopalliance/1.0/aopalliance-1.0-sources.jar","isSystem":false,"isOwn":false,"isTest":false,"isJavaContent":false},{"kind":"binary","path":"C:\\Users\\L460\\.m2\\repository\\org\\aspectj\\aspectjweaver\\1.8.6\\aspectjweaver-1.8.6.jar","sourceContainerUrl":"file:/C:/Users/L460/.m2/repository/org/aspectj/aspectjweaver/1.8.6/aspectjweaver-1.8.6-sources.jar","javadocContainerUrl":"file:/C:/Users/L460/.m2/repository/org/aspectj/aspectjweaver/1.8.6/aspectjweaver-1.8.6-javadoc.jar","isSystem":false,"isOwn":false,"isTest":false,"isJavaContent":false},{"kind":"binary","path":"C:\\Users\\L460\\.m2\\repository\\org\\springframework\\spring-oxm\\4.2.5.RELEASE\\spring-oxm-4.2.5.RELEASE.jar","sourceContainerUrl":"file:/C:/Users/L460/.m2/repository/org/springframework/spring-oxm/4.2.5.RELEASE/spring-oxm-4.2.5.RELEASE-sources.jar","javadocContainerUrl":"file:/C:/Users/L460/.m2/repository/org/springframework/spring-oxm/4.2.5.RELEASE/spring-oxm-4.2.5.RELEASE-javadoc.jar","isSystem":false,"isOwn":false,"isTest":false,"isJavaContent":false},{"kind":"binary","path":"C:\\Users\\L460\\.m2\\repository\\org\\springframework\\spring-tx\\4.2.5.RELEASE\\spring-tx-4.2.5.RELEASE.jar","sourceContainerUrl":"file:/C:/Users/L460/.m2/repository/org/springframework/spring-tx/4.2.5.RELEASE/spring-tx-4.2.5.RELEASE-sources.jar","javadocContainerUrl":"file:/C:/Users/L460/.m2/repository/org/springframework/spring-tx/4.2.5.RELEASE/spring-tx-4.2.5.RELEASE-javadoc.jar","isSystem":false,"isOwn":false,"isTest":false,"isJavaContent":false},{"kind":"binary","path":"C:\\Users\\L460\\.m2\\repository\\org\\springframework\\spring-messaging\\4.3.8.RELEASE\\spring-messaging-4.3.8.RELEASE.jar","sourceContainerUrl":"file:/C:/Users/L460/.m2/repository/org/springframework/spring-messaging/4.3.8.RELEASE/spring-messaging-4.3.8.RELEASE-sources.jar","javadocContainerUrl":"file:/C:/Users/L460/.m2/repository/org/springframework/spring-messaging/4.3.8.RELEASE/spring-messaging-4.3.8.RELEASE-javadoc.jar","isSystem":false,"isOwn":false,"isTest":false,"isJavaContent":false},{"kind":"binary","path":"C:\\Users\\L460\\.m2\\repository\\javax\\websocket\\javax.websocket-api\\1.1\\javax.websocket-api-1.1.jar","sourceContainerUrl":"file:/C:/Users/L460/.m2/repository/javax/websocket/javax.websocket-api/1.1/javax.websocket-api-1.1-sources.jar","javadocContainerUrl":"file:/C:/Users/L460/.m2/repository/javax/websocket/javax.websocket-api/1.1/javax.websocket-api-1.1-javadoc.jar","isSystem":false,"isOwn":false,"isTest":false,"isJavaContent":false},{"kind":"binary","path":"C:\\Users\\L460\\.m2\\repository\\org\\slf4j\\slf4j-api\\1.7.25\\slf4j-api-1.7.25.jar","sourceContainerUrl":"file:/C:/Users/L460/.m2/repository/org/slf4j/slf4j-api/1.7.25/slf4j-api-1.7.25-sources.jar","javadocContainerUrl":"file:/C:/Users/L460/.m2/repository/org/slf4j/slf4j-api/1.7.25/slf4j-api-1.7.25-javadoc.jar","isSystem":false,"isOwn":false,"isTest":false,"isJavaContent":false},{"kind":"binary","path":"C:\\Users\\L460\\.m2\\repository\\ch\\qos\\logback\\logback-core\\1.1.7\\logback-core-1.1.7.jar","sourceContainerUrl":"file:/C:/Users/L460/.m2/repository/ch/qos/logback/logback-core/1.1.7/logback-core-1.1.7-sources.jar","javadocContainerUrl":"file:/C:/Users/L460/.m2/repository/ch/qos/logback/logback-core/1.1.7/logback-core-1.1.7-javadoc.jar","isSystem":false,"isOwn":false,"isTest":false,"isJavaContent":false},{"kind":"binary","path":"C:\\Users\\L460\\.m2\\repository\\ch\\qos\\logback\\logback-classic\\1.1.7\\logback-classic-1.1.7.jar","sourceContainerUrl":"file:/C:/Users/L460/.m2/repository/ch/qos/logback/logback-classic/1.1.7/logback-classic-1.1.7-sources.jar","javadocContainerUrl":"file:/C:/Users/L460/.m2/repository/ch/qos/logback/logback-classic/1.1.7/logback-classic-1.1.7-javadoc.jar","isSystem":false,"isOwn":false,"isTest":false,"isJavaContent":false},{"kind":"binary","path":"C:\\Users\\L460\\.m2\\repository\\com\\fasterxml\\jackson\\core\\jackson-core\\2.1.0\\jackson-core-2.1.0.jar","sourceContainerUrl":"file:/C:/Users/L460/.m2/repository/com/fasterxml/jackson/core/jackson-core/2.1.0/jackson-core-2.1.0-sources.jar","javadocContainerUrl":"file:/C:/Users/L460/.m2/repository/com/fasterxml/jackson/core/jackson-core/2.1.0/jackson-core-2.1.0-javadoc.jar","isSystem":false,"isOwn":false,"isTest":false,"isJavaContent":false},{"kind":"binary","path":"C:\\Users\\L460\\.m2\\repository\\com\\fasterxml\\jackson\\core\\jackson-databind\\2.1.0\\jackson-databind-2.1.0.jar","sourceContainerUrl":"file:/C:/Users/L460/.m2/repository/com/fasterxml/jackson/core/jackson-databind/2.1.0/jackson-databind-2.1.0-sources.jar","javadocContainerUrl":"file:/C:/Users/L460/.m2/repository/com/fasterxml/jackson/core/jackson-databind/2.1.0/jackson-databind-2.1.0-javadoc.jar","isSystem":false,"isOwn":false,"isTest":false,"isJavaContent":false},{"kind":"binary","path":"C:\\Users\\L460\\.m2\\repository\\com\\fasterxml\\jackson\\core\\jackson-annotations\\2.1.0\\jackson-annotations-2.1.0.jar","sourceContainerUrl":"file:/C:/Users/L460/.m2/repository/com/fasterxml/jackson/core/jackson-annotations/2.1.0/jackson-annotations-2.1.0-sources.jar","javadocContainerUrl":"file:/C:/Users/L460/.m2/repository/com/fasterxml/jackson/core/jackson-annotations/2.1.0/jackson-annotations-2.1.0-javadoc.jar","isSystem":false,"isOwn":false,"isTest":false,"isJavaContent":false},{"kind":"binary","path":"C:\\Users\\L460\\.m2\\repository\\commons-fileupload\\commons-fileupload\\1.3.2\\commons-fileupload-1.3.2.jar","sourceContainerUrl":"file:/C:/Users/L460/.m2/repository/commons-fileupload/commons-fileupload/1.3.2/commons-fileupload-1.3.2-sources.jar","javadocContainerUrl":"file:/C:/Users/L460/.m2/repository/commons-fileupload/commons-fileupload/1.3.2/commons-fileupload-1.3.2-javadoc.jar","isSystem":false,"isOwn":false,"isTest":false,"isJavaContent":false},{"kind":"binary","path":"C:\\Users\\L460\\.m2\\repository\\commons-io\\commons-io\\2.2\\commons-io-2.2.jar","sourceContainerUrl":"file:/C:/Users/L460/.m2/repository/commons-io/commons-io/2.2/commons-io-2.2-sources.jar","javadocContainerUrl":"file:/C:/Users/L460/.m2/repository/commons-io/commons-io/2.2/commons-io-2.2-javadoc.jar","isSystem":false,"isOwn":false,"isTest":false,"isJavaContent":false},{"kind":"binary","path":"C:\\Users\\L460\\.m2\\repository\\junit\\junit\\4.11\\junit-4.11.jar","sourceContainerUrl":"file:/C:/Users/L460/.m2/repository/junit/junit/4.11/junit-4.11-sources.jar","javadocContainerUrl":"file:/C:/Users/L460/.m2/repository/junit/junit/4.11/junit-4.11-javadoc.jar","isSystem":false,"isOwn":false,"isTest":false,"isJavaContent":false},{"kind":"binary","path":"C:\\Users\\L460\\.m2\\repository\\org\\hamcrest\\hamcrest-core\\1.3\\hamcrest-core-1.3.jar","sourceContainerUrl":"file:/C:/Users/L460/.m2/repository/org/hamcrest/hamcrest-core/1.3/hamcrest-core-1.3-sources.jar","javadocContainerUrl":"file:/C:/Users/L460/.m2/repository/org/hamcrest/hamcrest-core/1.3/hamcrest-core-1.3-javadoc.jar","isSystem":false,"isOwn":false,"isTest":false,"isJavaContent":false},{"kind":"binary","path":"C:\\Users\\L460\\.m2\\repository\\org\\springframework\\data\\spring-data-redis\\1.7.2.RELEASE\\spring-data-redis-1.7.2.RELEASE.jar","sourceContainerUrl":"file:/C:/Users/L460/.m2/repository/org/springframework/data/spring-data-redis/1.7.2.RELEASE/spring-data-redis-1.7.2.RELEASE-sources.jar","javadocContainerUrl":"file:/C:/Users/L460/.m2/repository/org/springframework/data/spring-data-redis/1.7.2.RELEASE/spring-data-redis-1.7.2.RELEASE-javadoc.jar","isSystem":false,"isOwn":false,"isTest":false,"isJavaContent":false},{"kind":"binary","path":"C:\\Users\\L460\\.m2\\repository\\org\\springframework\\data\\spring-data-keyvalue\\1.1.2.RELEASE\\spring-data-keyvalue-1.1.2.RELEASE.jar","sourceContainerUrl":"file:/C:/Users/L460/.m2/repository/org/springframework/data/spring-data-keyvalue/1.1.2.RELEASE/spring-data-keyvalue-1.1.2.RELEASE-sources.jar","javadocContainerUrl":"file:/C:/Users/L460/.m2/repository/org/springframework/data/spring-data-keyvalue/1.1.2.RELEASE/spring-data-keyvalue-1.1.2.RELEASE-javadoc.jar","isSystem":false,"isOwn":false,"isTest":false,"isJavaContent":false},{"kind":"binary","path":"C:\\Users\\L460\\.m2\\repository\\com\\mchange\\c3p0\\0.9.5.2\\c3p0-0.9.5.2.jar","sourceContainerUrl":"file:/C:/Users/L460/.m2/repository/com/mchange/c3p0/0.9.5.2/c3p0-0.9.5.2-sources.jar","javadocContainerUrl":"file:/C:/Users/L460/.m2/repository/com/mchange/c3p0/0.9.5.2/c3p0-0.9.5.2-javadoc.jar","isSystem":false,"isOwn":false,"isTest":false,"isJavaContent":false},{"kind":"binary","path":"C:\\Users\\L460\\.m2\\repository\\com\\mchange\\mchange-commons-java\\0.2.11\\mchange-commons-java-0.2.11.jar","sourceContainerUrl":"file:/C:/Users/L460/.m2/repository/com/mchange/mchange-commons-java/0.2.11/mchange-commons-java-0.2.11-sources.jar","javadocContainerUrl":"file:/C:/Users/L460/.m2/repository/com/mchange/mchange-commons-java/0.2.11/mchange-commons-java-0.2.11-javadoc.jar","isSystem":false,"isOwn":false,"isTest":false,"isJavaContent":false},{"kind":"binary","path":"C:\\Users\\L460\\.m2\\repository\\javax\\servlet\\servlet-api\\2.5\\servlet-api-2.5.jar","sourceContainerUrl":"file:/C:/Users/L460/.m2/repository/javax/servlet/servlet-api/2.5/servlet-api-2.5-sources.jar","isSystem":false,"isOwn":false,"isTest":false,"isJavaContent":false},{"kind":"binary","path":"C:\\Users\\L460\\.m2\\repository\\org\\quartz-scheduler\\quartz\\2.2.1\\quartz-2.2.1.jar","sourceContainerUrl":"file:/C:/Users/L460/.m2/repository/org/quartz-scheduler/quartz/2.2.1/quartz-2.2.1-sources.jar","javadocContainerUrl":"file:/C:/Users/L460/.m2/repository/org/quartz-scheduler/quartz/2.2.1/quartz-2.2.1-javadoc.jar","isSystem":false,"isOwn":false,"isTest":false,"isJavaContent":false},{"kind":"binary","path":"C:\\Users\\L460\\.m2\\repository\\c3p0\\c3p0\\0.9.1.1\\c3p0-0.9.1.1.jar","sourceContainerUrl":"file:/C:/Users/L460/.m2/repository/c3p0/c3p0/0.9.1.1/c3p0-0.9.1.1-sources.jar","javadocContainerUrl":"file:/C:/Users/L460/.m2/repository/c3p0/c3p0/0.9.1.1/c3p0-0.9.1.1-javadoc.jar","isSystem":false,"isOwn":false,"isTest":false,"isJavaContent":false},{"kind":"binary","path":"C:\\Users\\L460\\.m2\\repository\\org\\quartz-scheduler\\quartz-jobs\\2.2.1\\quartz-jobs-2.2.1.jar","sourceContainerUrl":"file:/C:/Users/L460/.m2/repository/org/quartz-scheduler/quartz-jobs/2.2.1/quartz-jobs-2.2.1-sources.jar","javadocContainerUrl":"file:/C:/Users/L460/.m2/repository/org/quartz-scheduler/quartz-jobs/2.2.1/quartz-jobs-2.2.1-javadoc.jar","isSystem":false,"isOwn":false,"isTest":false,"isJavaContent":false},{"kind":"binary","path":"C:\\Users\\L460\\.m2\\repository\\mysql\\mysql-connector-java\\5.1.35\\mysql-connector-java-5.1.35.jar","sourceContainerUrl":"file:/C:/Users/L460/.m2/repository/mysql/mysql-connector-java/5.1.35/mysql-connector-java-5.1.35-sources.jar","isSystem":false,"isOwn":false,"isTest":false,"isJavaContent":false},{"kind":"binary","path":"C:\\Users\\L460\\.m2\\repository\\redis\\clients\\jedis\\2.8.1\\jedis-2.8.1.jar","sourceContainerUrl":"file:/C:/Users/L460/.m2/repository/redis/clients/jedis/2.8.1/jedis-2.8.1-sources.jar","javadocContainerUrl":"file:/C:/Users/L460/.m2/repository/redis/clients/jedis/2.8.1/jedis-2.8.1-javadoc.jar","isSystem":false,"isOwn":false,"isTest":false,"isJavaContent":false},{"kind":"binary","path":"C:\\Users\\L460\\.m2\\repository\\org\\apache\\commons\\commons-pool2\\2.4.2\\commons-pool2-2.4.2.jar","sourceContainerUrl":"file:/C:/Users/L460/.m2/repository/org/apache/commons/commons-pool2/2.4.2/commons-pool2-2.4.2-sources.jar","javadocContainerUrl":"file:/C:/Users/L460/.m2/repository/org/apache/commons/commons-pool2/2.4.2/commons-pool2-2.4.2-javadoc.jar","isSystem":false,"isOwn":false,"isTest":false,"isJavaContent":false},{"kind":"binary","path":"C:\\Users\\L460\\.m2\\repository\\dom4j\\dom4j\\1.6.1\\dom4j-1.6.1.jar","sourceContainerUrl":"file:/C:/Users/L460/.m2/repository/dom4j/dom4j/1.6.1/dom4j-1.6.1-sources.jar","isSystem":false,"isOwn":false,"isTest":false,"isJavaContent":false},{"kind":"binary","path":"C:\\Users\\L460\\.m2\\repository\\xml-apis\\xml-apis\\1.0.b2\\xml-apis-1.0.b2.jar","sourceContainerUrl":"file:/C:/Users/L460/.m2/repository/xml-apis/xml-apis/1.0.b2/xml-apis-1.0.b2-sources.jar","isSystem":false,"isOwn":false,"isTest":false,"isJavaContent":false},{"kind":"binary","path":"C:\\Users\\L460\\.m2\\repository\\org\\freemarker\\freemarker\\2.3.23\\freemarker-2.3.23.jar","sourceContainerUrl":"file:/C:/Users/L460/.m2/repository/org/freemarker/freemarker/2.3.23/freemarker-2.3.23-sources.jar","javadocContainerUrl":"file:/C:/Users/L460/.m2/repository/org/freemarker/freemarker/2.3.23/freemarker-2.3.23-javadoc.jar","isSystem":false,"isOwn":false,"isTest":false,"isJavaContent":false},{"kind":"binary","path":"C:\\Users\\L460\\.m2\\repository\\commons-dbcp\\commons-dbcp\\1.4\\commons-dbcp-1.4.jar","sourceContainerUrl":"file:/C:/Users/L460/.m2/repository/commons-dbcp/commons-dbcp/1.4/commons-dbcp-1.4-sources.jar","javadocContainerUrl":"file:/C:/Users/L460/.m2/repository/commons-dbcp/commons-dbcp/1.4/commons-dbcp-1.4-javadoc.jar","isSystem":false,"isOwn":false,"isTest":false,"isJavaContent":false},{"kind":"binary","path":"C:\\Users\\L460\\.m2\\repository\\commons-pool\\commons-pool\\1.5.4\\commons-pool-1.5.4.jar","sourceContainerUrl":"file:/C:/Users/L460/.m2/repository/commons-pool/commons-pool/1.5.4/commons-pool-1.5.4-sources.jar","javadocContainerUrl":"file:/C:/Users/L460/.m2/repository/commons-pool/commons-pool/1.5.4/commons-pool-1.5.4-javadoc.jar","isSystem":false,"isOwn":false,"isTest":false,"isJavaContent":false},{"kind":"binary","path":"C:\\Users\\L460\\.m2\\repository\\javax\\mail\\javax.mail-api\\1.5.5\\javax.mail-api-1.5.5.jar","sourceContainerUrl":"file:/C:/Users/L460/.m2/repository/javax/mail/javax.mail-api/1.5.5/javax.mail-api-1.5.5-sources.jar","javadocContainerUrl":"file:/C:/Users/L460/.m2/repository/javax/mail/javax.mail-api/1.5.5/javax.mail-api-1.5.5-javadoc.jar","isSystem":false,"isOwn":false,"isTest":false,"isJavaContent":false},{"kind":"binary","path":"C:\\Users\\L460\\.m2\\repository\\org\\apache\\commons\\commons-email\\1.4\\commons-email-1.4.jar","sourceContainerUrl":"file:/C:/Users/L460/.m2/repository/org/apache/commons/commons-email/1.4/commons-email-1.4-sources.jar","javadocContainerUrl":"file:/C:/Users/L460/.m2/repository/org/apache/commons/commons-email/1.4/commons-email-1.4-javadoc.jar","isSystem":false,"isOwn":false,"isTest":false,"isJavaContent":false},{"kind":"binary","path":"C:\\Users\\L460\\.m2\\repository\\com\\sun\\mail\\javax.mail\\1.5.2\\javax.mail-1.5.2.jar","sourceContainerUrl":"file:/C:/Users/L460/.m2/repository/com/sun/mail/javax.mail/1.5.2/javax.mail-1.5.2-sources.jar","javadocContainerUrl":"file:/C:/Users/L460/.m2/repository/com/sun/mail/javax.mail/1.5.2/javax.mail-1.5.2-javadoc.jar","isSystem":false,"isOwn":false,"isTest":false,"isJavaContent":false},{"kind":"binary","path":"C:\\Users\\L460\\.m2\\repository\\javax\\activation\\activation\\1.1.1\\activation-1.1.1.jar","sourceContainerUrl":"file:/C:/Users/L460/.m2/repository/javax/activation/activation/1.1.1/activation-1.1.1-sources.jar","isSystem":false,"isOwn":false,"isTest":false,"isJavaContent":false},{"kind":"binary","path":"C:\\Users\\L460\\.m2\\repository\\org\\javalite\\activejdbc\\1.4.13\\activejdbc-1.4.13.jar","sourceContainerUrl":"file:/C:/Users/L460/.m2/repository/org/javalite/activejdbc/1.4.13/activejdbc-1.4.13-sources.jar","javadocContainerUrl":"file:/C:/Users/L460/.m2/repository/org/javalite/activejdbc/1.4.13/activejdbc-1.4.13-javadoc.jar","isSystem":false,"isOwn":false,"isTest":false,"isJavaContent":false},{"kind":"binary","path":"C:\\Users\\L460\\.m2\\repository\\org\\javalite\\javalite-common\\1.4.13\\javalite-common-1.4.13.jar","sourceContainerUrl":"file:/C:/Users/L460/.m2/repository/org/javalite/javalite-common/1.4.13/javalite-common-1.4.13-sources.jar","javadocContainerUrl":"file:/C:/Users/L460/.m2/repository/org/javalite/javalite-common/1.4.13/javalite-common-1.4.13-javadoc.jar","isSystem":false,"isOwn":false,"isTest":false,"isJavaContent":false},{"kind":"binary","path":"C:\\Users\\L460\\.m2\\repository\\org\\codehaus\\jackson\\jackson-core-asl\\1.9.13\\jackson-core-asl-1.9.13.jar","sourceContainerUrl":"file:/C:/Users/L460/.m2/repository/org/codehaus/jackson/jackson-core-asl/1.9.13/jackson-core-asl-1.9.13-sources.jar","javadocContainerUrl":"file:/C:/Users/L460/.m2/repository/org/codehaus/jackson/jackson-core-asl/1.9.13/jackson-core-asl-1.9.13-javadoc.jar","isSystem":false,"isOwn":false,"isTest":false,"isJavaContent":false},{"kind":"binary","path":"C:\\Users\\L460\\.m2\\repository\\org\\codehaus\\jackson\\jackson-mapper-asl\\1.9.13\\jackson-mapper-asl-1.9.13.jar","sourceContainerUrl":"file:/C:/Users/L460/.m2/repository/org/codehaus/jackson/jackson-mapper-asl/1.9.13/jackson-mapper-asl-1.9.13-sources.jar","javadocContainerUrl":"file:/C:/Users/L460/.m2/repository/org/codehaus/jackson/jackson-mapper-asl/1.9.13/jackson-mapper-asl-1.9.13-javadoc.jar","isSystem":false,"isOwn":false,"isTest":false,"isJavaContent":false},{"kind":"binary","path":"C:\\Users\\L460\\.m2\\repository\\org\\javalite\\app-config\\1.4.13\\app-config-1.4.13.jar","sourceContainerUrl":"file:/C:/Users/L460/.m2/repository/org/javalite/app-config/1.4.13/app-config-1.4.13-sources.jar","javadocContainerUrl":"file:/C:/Users/L460/.m2/repository/org/javalite/app-config/1.4.13/app-config-1.4.13-javadoc.jar","isSystem":false,"isOwn":false,"isTest":false,"isJavaContent":false},{"kind":"source","path":"D:\\myGit\\SSFBlog\\src\\parent\\web\\src\\main\\java","outputFolder":"D:\\myGit\\SSFBlog\\src\\parent\\web\\target\\classes","javadocContainerUrl":"file:/D:/myGit/SSFBlog/src/parent/web/target/site/apidocs","isSystem":false,"isOwn":true,"isTest":false,"isJavaContent":true},{"kind":"source","path":"D:\\myGit\\SSFBlog\\src\\parent\\web\\src\\test\\java","outputFolder":"D:\\myGit\\SSFBlog\\src\\parent\\web\\target\\test-classes","javadocContainerUrl":"file:/D:/myGit/SSFBlog/src/parent/web/target/site/apidocs","isSystem":false,"isOwn":true,"isTest":true,"isJavaContent":true},{"kind":"source","path":"D:\\myGit\\SSFBlog\\src\\parent\\web\\src\\main\\resources","outputFolder":"D:\\myGit\\SSFBlog\\src\\parent\\web\\target\\classes","isSystem":false,"isOwn":true,"isTest":false,"isJavaContent":false},{"kind":"source","path":"D:\\myGit\\SSFBlog\\src\\parent\\web\\src\\test\\resources","outputFolder":"D:\\myGit\\SSFBlog\\src\\parent\\web\\target\\test-classes","isSystem":false,"isOwn":true,"isTest":true,"isJavaContent":false},{"kind":"source","path":"D:\\myGit\\SSFBlog\\src\\parent\\web\\src\\test\\java","outputFolder":"D:\\myGit\\SSFBlog\\src\\parent\\web\\target\\test-classes","javadocContainerUrl":"file:/D:/myGit/SSFBlog/src/parent/web/target/site/apidocs","isSystem":false,"isOwn":true,"isTest":false,"isJavaContent":false}]}